topsis_101703295/topsis.py
topsis_101703295-0.0.1.dist-info/LICENSE
topsis_101703295-0.0.1.dist-info/METADATA
topsis_101703295-0.0.1.dist-info/WHEEL
topsis_101703295-0.0.1.dist-info/entry_points.txt
topsis_101703295-0.0.1.dist-info/top_level.txt
topsis_101703295-0.0.1.dist-info/RECORD
