Metadata-Version: 2.1
Name: topsis-101703295
Version: 0.0.1
Summary: A small example package
Home-page: https://github.com/kv6737/topsis
Author: Kshitiz varshney
Author-email: kvarshney_be17@thapar.edu
License: UNKNOWN
Platform: UNKNOWN
Classifier: Programming Language :: Python :: 3
Classifier: License :: OSI Approved :: MIT License
Classifier: Operating System :: OS Independent
Requires-Dist: scipy
Requires-Dist: tabulate
Requires-Dist: numpy
Requires-Dist: pandas
